Metadata-Version: 2.1
Name: crydreamcode
Version: 1.0.1
Summary: CoreCode
Author: CryDream
License: None
License-File: LICENSE
